shaggy/__init__.py
shaggy/hunt.py
shaggy/output.py
shaggy/sources.py
shaggy-1.0.8.dist-info/LICENSE
shaggy-1.0.8.dist-info/METADATA
shaggy-1.0.8.dist-info/WHEEL
shaggy-1.0.8.dist-info/entry_points.txt
shaggy-1.0.8.dist-info/top_level.txt
shaggy-1.0.8.dist-info/RECORD
