Metadata-Version: 2.1
Name: shaggy
Version: 1.0.8
Summary: Discover and connect with social media accounts across multiple platforms using just a username with SocialTrackr, the ultimate account hunting software.
Home-page: https://github.com/mauro-balades/shaggy
Author: Mauro Baladés
Author-email: mauro.balades@tutanota.com
License: MIT
Classifier: Development Status :: 5 - Production/Stable
Classifier: Intended Audience :: Developers
Classifier: License :: OSI Approved :: MIT License
Classifier: Programming Language :: Python :: 3
Classifier: Programming Language :: Python :: 3.6
Classifier: Programming Language :: Python :: 3.7
Classifier: Programming Language :: Python :: 3.8
Classifier: Programming Language :: Python :: 3.9
License-File: LICENSE
Requires-Dist: tqdm (==4.65.0)
Requires-Dist: colorama (==0.4.6)
Requires-Dist: termcolor (==2.3.0)
Requires-Dist: requests (==2.31.0)
